README.md
setup.py
gesiel/__init__.py
gesiel/exceptions.py
gesiel/fields.py
gesiel/messages.py
gesiel/schema.py
gesiel/validators.py
gesiel.egg-info/PKG-INFO
gesiel.egg-info/SOURCES.txt
gesiel.egg-info/dependency_links.txt
gesiel.egg-info/top_level.txt